Workbook

Sheet Read Me
A1: Nota — Financial Model
A2: Pre-seed raise: $250,000 CAD · 12 months · built 2026-08-16
A4: HOW TO READ THIS WORKBOOK
A5: Colour legend
A6: Blue text | B6: A hardcoded input or scenario lever. These are the ONLY cells you should edit.
A7: Black text | B7: A formula. Do not overwrite — it recalculates from the blue inputs.
A8: Green text | B8: A link to another sheet in this workbook.
A9: Yellow fill | B9: A key assumption worth arguing about in a diligence conversation.
A11: Sheets
A12: Assumptions | B12: Every driver in the model. Change a number here and the whole workbook moves.
A13: Y1 Monthly | B13: Month-by-month year one: demand ramp, fill rate, revenue, burn, cash runway.
A14: P&L 3Y | B14: Three-year P&L summary, Y1 rolled up from the monthly sheet.
A15: Use of Funds | B15: How the $250,000 is spent, and the monthly opex schedule that drives Y1 cash.
A16: Unit Economics | B16: Per-act contribution, CAC, payback, notary LTV.
A17: Market Sizing | B17: Bottom-up TAM / SAM / SOM with sources.
A19: Currency | B19: All figures are Canadian dollars (CAD), nominal, no inflation adjustment.
A20: Fiscal years | B20: Y1 = Sep 2026–Aug 2027, Y2 = Sep 2027–Aug 2028, Y3 = Sep 2028–Aug 2029.
A22: THE THREE ASSUMPTIONS THAT CARRY THE MODEL
A23: 1. Urgency premium | B23: Clients pay materially more for a near-term signing date. Falsification test: realised premium by tier, visible month 6.
A24: 2. Supply elasticity | B24: Notaries will sell short-notice availability. Falsification test: fill rate on prioritaire/urgence tiers, visible month 5.
A25: 3. Déontologie-safe fee | B25: A client-side service fee is not fee-sharing under the Code de déontologie. Falsification test: written legal opinion, month 2.
A27: Note | B27: Revenue is modelled as a CLIENT-SIDE service fee on top of the notary's fee — NOT a commission deducted
B28: from the notary's honoraires. See docs/business-plan.md §2.2. The notary receives 100% of their fee.

Sheet Assumptions
A1: Assumptions
A2: Blue = editable input. Everything else in the workbook derives from this sheet.
A4: SCENARIO LEVERS
A5: Take rate (client service fee, % of act value) | B5: 0.1 | E5: Charged to the CLIENT on top of the act. Notary keeps 100% of honoraires.
A6: Nota absorbs act payment-processing cost? (Yes/No) | B6: No | E6: No = notary's connected account bears Stripe on the act (standard destination charge). Yes = Nota absorbs it.
A7: Payment processing rate | B7: 0.03 | E7: Stripe ~2.9% + $0.30; rounded to 3.0% blended.
A8: Variable cost per completed act | B8: 8 | E8: Identity verification, document storage, transactional email, per-act compute.
A10: SERVICE MIX AND REALISED ACT VALUE
A11: Service | B11: Floor price | C11: Realised avg | D11: Y1 mix | E11: Realised avg = floor × observed urgency premium. Floors from ADR 0006.
A12: Testament et mandat de protection | B12: 650 | C12: 900 | D12: 0.5
A13: Procuration | B13: 295 | C13: 420 | D13: 0.3
A14: Refinancement hypothécaire | B14: 2000 | C14: 2400 | D14: 0.2
A15: Mix check (must equal 100%) | D15: =SUM(D12:D14) -> 1
A16: Y1 blended realised act value | C16: =SUMPRODUCT(C12:C14,D12:D14) -> 1056
A18: ANNUAL DRIVERS
B19: Y1 | C19: Y2 | D19: Y3
A20: Notaries on platform (end of year) | B20: 30 | C20: 220 | D20: 700 | E20: Y1 = Québec City only (~400 local notaries). Y2 = province-wide (~3,900).
A21: Bids posted | B21: ='Y1 Monthly'!N6 -> 434 | C21: 4912 | D21: 17742
A22: Fill rate (share of bids retained) | B22: =IFERROR('Y1 Monthly'!N8/B21,0) -> 0.56221198 | C22: 0.57 | D22: 0.62 | E22: THE metric. Below ~40% the market is not clearing; above ~60% the flywheel is real.
A23: Acts completed | B23: ='Y1 Monthly'!N8 -> 244 | C23: =ROUND(C21*C22,0) -> 2800 | D23: =ROUND(D21*D22,0) -> 11000
A24: Average realised act value | B24: =Assumptions!$C$16 -> 1056 | C24: 1150 | D24: 1450 | E24: Y3 rises as the act catalogue widens toward residential closings.
A25: Blended client CAC | B25: =IFERROR('Use of Funds'!C16/B23,0) -> 163.93443 | C25: 55 | D25: 40 | E25: Y1 derived from the marketing budget ÷ acts. Y2–Y3 assume organic + referral channels compound.
A26: Operating expense | B26: ='Use of Funds'!C13 -> 250000 | C26: 720000 | D26: 1850000
A27: Headcount (FTE, end of year) | B27: 1 | C27: 4 | D27: 10
A29: FUNDING
A30: Pre-seed raise | B30: 250000 | E30: SAFE or convertible note with an angel lead.
A31: Opening cash before raise | B31: 0
A32: Non-dilutive credits (SR&ED / QC R&D), Y1 | B32: 0 | E32: Deliberately modelled at zero. Treated as runway upside (~2–3 months), not budgeted revenue.

Sheet Use of Funds
A1: Use of Funds — $250,000 over 12 months
A2: Column C is the 12-month total; columns D–O are the monthly opex schedule that drives Y1 cash.
A4: Line | C4: Total | D4: M1 | E4: M2 | F4: M3 | G4: M4 | H4: M5 | I4: M6 | J4: M7 | K4: M8 | L4: M9 | M4: M10 | N4: M11 | O4: M12
A5: Founder salary | C5: =SUM(D5:O5) -> 96000 | D5: 8000 | E5: 8000 | F5: 8000 | G5: 8000 | H5: 8000 | I5: 8000 | J5: 8000 | K5: 8000 | L5: 8000 | M5: 8000 | N5: 8000 | O5: 8000
A6: Legal — déontologie opinion, Chambre, incorporation, Law 25 | C6: =SUM(D6:O6) -> 20000 | D6: 12000 | E6: 8000 | F6: 0 | G6: 0 | H6: 0 | I6: 0 | J6: 0 | K6: 0 | L6: 0 | M6: 0 | N6: 0 | O6: 0
A7: Notary advisor (part-time, practising) | C7: =SUM(D7:O7) -> 25000 | D7: 2084 | E7: 2084 | F7: 2084 | G7: 2083 | H7: 2083 | I7: 2083 | J7: 2083 | K7: 2083 | L7: 2083 | M7: 2083 | N7: 2083 | O7: 2084
A8: Design / front-end contractor | C8: =SUM(D8:O8) -> 25000 | D8: 0 | E8: 8334 | F8: 8333 | G8: 8333 | H8: 0 | I8: 0 | J8: 0 | K8: 0 | L8: 0 | M8: 0 | N8: 0 | O8: 0
A9: Client acquisition | C9: =SUM(D9:O9) -> 40000 | D9: 0 | E9: 1000 | F9: 2000 | G9: 3000 | H9: 3500 | I9: 4000 | J9: 4500 | K9: 4500 | L9: 5000 | M9: 5000 | N9: 4000 | O9: 3500
A10: Notary acquisition (field, congrès, travel) | C10: =SUM(D10:O10) -> 15000 | D10: 4000 | E10: 4000 | F10: 3000 | G10: 1000 | H10: 500 | I10: 500 | J10: 500 | K10: 500 | L10: 250 | M10: 250 | N10: 250 | O10: 250
A11: Infrastructure, Stripe, certificates, insurance, tooling | C11: =SUM(D11:O11) -> 12000 | D11: 1000 | E11: 1000 | F11: 1000 | G11: 1000 | H11: 1000 | I11: 1000 | J11: 1000 | K11: 1000 | L11: 1000 | M11: 1000 | N11: 1000 | O11: 1000
A12: Contingency (~7%) | C12: =SUM(D12:O12) -> 17000 | D12: 1417 | E12: 1417 | F12: 1417 | G12: 1417 | H12: 1417 | I12: 1417 | J12: 1417 | K12: 1417 | L12: 1417 | M12: 1417 | N12: 1417 | O12: 1413
A13: TOTAL OPERATING EXPENSE | C13: =SUM(C5:C12) -> 250000 | D13: =SUM(D5:D12) -> 28501 | E13: =SUM(E5:E12) -> 33835 | F13: =SUM(F5:F12) -> 25834 | G13: =SUM(G5:G12) -> 24833 | H13: =SUM(H5:H12) -> 16500 | I13: =SUM(I5:I12) -> 17000 | J13: =SUM(J5:J12) -> 17500 | ... O13: =SUM(O5:O12) -> 16247
A14: Raise ($250,000) less total spend — must be ≥ 0 | C14: =Assumptions!$B$30-C13 -> 0
A16: Marketing total (client acquisition), used for Y1 CAC | C16: =C9 -> 40000
A17: Average monthly burn | C17: =C13/12 -> 20833.333
A19: Note: legal spend is front-loaded on purpose — the déontologie opinion (§2.2 of the plan) unblocks everything else.
A20: Note: client acquisition ramps with demand rather than front-loading, because supply must reach ~25 notaries first.

Sheet Y1 Monthly
A1: Year 1 — monthly build
A2: Québec City. Blue cells are the demand ramp and fill-rate curve — the two things Phase 1 exists to test.
B4: M1 | C4: M2 | D4: M3 | E4: M4 | F4: M5 | G4: M6 | H4: M7 | I4: M8 | J4: M9 | K4: M10 | L4: M11 | M4: M12 | N4: Y1 Total
A5: Notaries on platform (cumulative) | B5: 6 | C5: 14 | D5: 25 | E5: 27 | F5: 28 | G5: 29 | H5: 30 | I5: 30 | J5: 30 | K5: 30 | L5: 30 | M5: 30 | N5: =M5 -> 30
A6: Bids posted | B6: 3 | C6: 5 | D6: 8 | E6: 12 | F6: 18 | G6: 25 | H6: 32 | I6: 42 | J6: 52 | K6: 64 | L6: 78 | M6: 95 | N6: =SUM(B6:M6) -> 434
A7: Fill rate | B7: 0.2 | C7: 0.25 | D7: 0.3 | E7: 0.35 | F7: 0.4 | G7: 0.45 | H7: 0.5 | I7: 0.55 | J7: 0.58 | K7: 0.6 | L7: 0.63 | M7: 0.65 | N7: =IFERROR(N8/N6,0) -> 0.56221198
A8: Acts completed | B8: =ROUND(B6*B7,0) -> 1 | C8: =ROUND(C6*C7,0) -> 1 | D8: =ROUND(D6*D7,0) -> 2 | E8: =ROUND(E6*E7,0) -> 4 | F8: =ROUND(F6*F7,0) -> 7 | G8: =ROUND(G6*G7,0) -> 11 | H8: =ROUND(H6*H7,0) -> 16 | I8: =ROUND(I6*I7,0) -> 23 | ... M8: =ROUND(M6*M7,0) -> 62 | N8: =SUM(B8:M8) -> 244
A9: Average realised act value | B9: =Assumptions!$C$16 -> 1056 | C9: =Assumptions!$C$16 -> 1056 | D9: =Assumptions!$C$16 -> 1056 | E9: =Assumptions!$C$16 -> 1056 | F9: =Assumptions!$C$16 -> 1056 | G9: =Assumptions!$C$16 -> 1056 | H9: =Assumptions!$C$16 -> 1056 | I9: =Assumptions!$C$16 -> 1056 | ... M9: =Assumptions!$C$16 -> 1056 | N9: =IFERROR(N10/N8,0) -> 1056
A10: GMV (act value transacted) | B10: =B8*B9 -> 1056 | C10: =C8*C9 -> 1056 | D10: =D8*D9 -> 2112 | E10: =E8*E9 -> 4224 | F10: =F8*F9 -> 7392 | G10: =G8*G9 -> 11616 | H10: =H8*H9 -> 16896 | I10: =I8*I9 -> 24288 | ... M10: =M8*M9 -> 65472 | N10: =SUM(B10:M10) -> 257664
A12: REVENUE AND GROSS PROFIT
A13: Net revenue (client service fee) | B13: =B10*Assumptions!$B$5 -> 105.6 | C13: =C10*Assumptions!$B$5 -> 105.6 | D13: =D10*Assumptions!$B$5 -> 211.2 | E13: =E10*Assumptions!$B$5 -> 422.4 | F13: =F10*Assumptions!$B$5 -> 739.2 | G13: =G10*Assumptions!$B$5 -> 1161.6 | H13: =H10*Assumptions!$B$5 -> 1689.6 | I13: =I10*Assumptions!$B$5 -> 2428.8 | ... M13: =M10*Assumptions!$B$5 -> 6547.2 | N13: =SUM(B13:M13) -> 25766.4
A14: Cost of revenue | B14: =-(B8*Assumptions!$B$8+B13*Assumptions!$B$7+IF(Assumptions!$B$6="Yes",B10*Assumptions!$B$7,0)) -> -11.168 | C14: =-(C8*Assumptions!$B$8+C13*Assumptions!$B$7+IF(Assumptions!$B$6="Yes",C10*Assumptions!$B$7,0)) -> -11.168 | D14: =-(D8*Assumptions!$B$8+D13*Assumptions!$B$7+IF(Assumptions!$B$6="Yes",D10*Assumptions!$B$7,0)) -> -22.336 | E14: =-(E8*Assumptions!$B$8+E13*Assumptions!$B$7+IF(Assumptions!$B$6="Yes",E10*Assumptions!$B$7,0)) -> -44.672 | F14: =-(F8*Assumptions!$B$8+F13*Assumptions!$B$7+IF(Assumptions!$B$6="Yes",F10*Assumptions!$B$7,0)) -> -78.176 | G14: =-(G8*Assumptions!$B$8+G13*Assumptions!$B$7+IF(Assumptions!$B$6="Yes",G10*Assumptions!$B$7,0)) -> -122.848 | H14: =-(H8*Assumptions!$B$8+H13*Assumptions!$B$7+IF(Assumptions!$B$6="Yes",H10*Assumptions!$B$7,0)) -> -178.688 | I14: =-(I8*Assumptions!$B$8+I13*Assumptions!$B$7+IF(Assumptions!$B$6="Yes",I10*Assumptions!$B$7,0)) -> -256.864 | ... M14: =-(M8*Assumptions!$B$8+M13*Assumptions!$B$7+IF(Assumptions!$B$6="Yes",M10*Assumptions!$B$7,0)) -> -692.416 | N14: =SUM(B14:M14) -> -2724.992
A15: Gross profit | B15: =B13+B14 -> 94.432 | C15: =C13+C14 -> 94.432 | D15: =D13+D14 -> 188.864 | E15: =E13+E14 -> 377.728 | F15: =F13+F14 -> 661.024 | G15: =G13+G14 -> 1038.752 | H15: =H13+H14 -> 1510.912 | I15: =I13+I14 -> 2171.936 | ... M15: =M13+M14 -> 5854.784 | N15: =SUM(B15:M15) -> 23041.408
A16: Gross margin | B16: =IFERROR(B15/B13,0) -> 0.89424242 | C16: =IFERROR(C15/C13,0) -> 0.89424242 | D16: =IFERROR(D15/D13,0) -> 0.89424242 | E16: =IFERROR(E15/E13,0) -> 0.89424242 | F16: =IFERROR(F15/F13,0) -> 0.89424242 | G16: =IFERROR(G15/G13,0) -> 0.89424242 | H16: =IFERROR(H15/H13,0) -> 0.89424242 | I16: =IFERROR(I15/I13,0) -> 0.89424242 | ... N16: =IFERROR(N15/N13,0) -> 0.89424242
A18: BURN AND RUNWAY
A19: Operating expense | B19: =-'Use of Funds'!D13 -> -28501 | C19: =-'Use of Funds'!E13 -> -33835 | D19: =-'Use of Funds'!F13 -> -25834 | E19: =-'Use of Funds'!G13 -> -24833 | F19: =-'Use of Funds'!H13 -> -16500 | G19: =-'Use of Funds'!I13 -> -17000 | H19: =-'Use of Funds'!J13 -> -17500 | I19: =-'Use of Funds'!K13 -> -17500 | ... M19: =-'Use of Funds'!O13 -> -16247 | N19: =SUM(B19:M19) -> -250000
A20: Net income | B20: =B15+B19 -> -28406.568 | C20: =C15+C19 -> -33740.568 | D20: =D15+D19 -> -25645.136 | E20: =E15+E19 -> -24455.272 | F20: =F15+F19 -> -15838.976 | G20: =G15+G19 -> -15961.248 | H20: =H15+H19 -> -15989.088 | I20: =I15+I19 -> -15328.064 | ... M20: =M15+M19 -> -10392.216 | N20: =SUM(B20:M20) -> -226958.59
A21: Opening cash | B21: =Assumptions!$B$30 -> 250000 | C21: =B22 -> 221593.43 | D21: =C22 -> 187852.86 | E21: =D22 -> 162207.73 | F21: =E22 -> 137752.46 | G21: =F22 -> 121913.48 | H21: =G22 -> 105952.23 | I21: =H22 -> 89963.144 | J21: =I22 -> 74635.08 | ... M21: =L22 -> 33433.624
A22: Closing cash | B22: =B21+B20 -> 221593.43 | C22: =C21+C20 -> 187852.86 | D22: =D21+D20 -> 162207.73 | E22: =E21+E20 -> 137752.46 | F22: =F21+F20 -> 121913.48 | G22: =G21+G20 -> 105952.23 | H22: =H21+H20 -> 89963.144 | I22: =I21+I20 -> 74635.08 | ... M22: =M21+M20 -> 23041.408 | N22: =M22 -> 23041.408
A24: Cumulative acts | B24: =B8 -> 1 | C24: =B24+C8 -> 2 | D24: =C24+D8 -> 4 | E24: =D24+E8 -> 8 | F24: =E24+F8 -> 15 | G24: =F24+G8 -> 26 | H24: =G24+H8 -> 42 | I24: =H24+I8 -> 65 | J24: =I24+J8 -> 95 | ... M24: =L24+M8 -> 244
A25: Cumulative net revenue | B25: =B13 -> 105.6 | C25: =B25+C13 -> 211.2 | D25: =C25+D13 -> 422.4 | E25: =D25+E13 -> 844.8 | F25: =E25+F13 -> 1584 | G25: =F25+G13 -> 2745.6 | H25: =G25+H13 -> 4435.2 | I25: =H25+I13 -> 6864 | J25: =I25+J13 -> 10032 | ... M25: =L25+M13 -> 25766.4
A27: Milestone: 25 notaries live (M3) · first 10 acts (M5) · fill rate >45% (M6) · exception layer shipped (M9) · fill >60% (M11)

Sheet P&L 3Y
A1: Three-year P&L
A2: Y1 rolls up from 'Y1 Monthly'. Y2–Y3 derive from the annual drivers on 'Assumptions'.
B4: Y1 2026-27 | C4: Y2 2027-28 | D4: Y3 2028-29
A5: Notaries on platform | B5: =Assumptions!B20 -> 30 | C5: =Assumptions!C20 -> 220 | D5: =Assumptions!D20 -> 700 | E5: Y1 Québec City only; Y2 province-wide matching live.
A6: Bids posted | B6: =Assumptions!B21 -> 434 | C6: =Assumptions!C21 -> 4912 | D6: =Assumptions!D21 -> 17742
A7: Fill rate | B7: =Assumptions!B22 -> 0.56221198 | C7: =Assumptions!C22 -> 0.57 | D7: =Assumptions!D22 -> 0.62 | E7: The single metric that says whether the marketplace is working.
A8: Acts completed | B8: =Assumptions!B23 -> 244 | C8: =Assumptions!C23 -> 2800 | D8: =Assumptions!D23 -> 11000
A9: Average realised act value | B9: =Assumptions!B24 -> 1056 | C9: =Assumptions!C24 -> 1150 | D9: =Assumptions!D24 -> 1450
A10: GMV | B10: =B8*B9 -> 257664 | C10: =C8*C9 -> 3220000 | D10: =D8*D9 -> 15950000
A12: Net revenue (client service fee) | B12: =B10*Assumptions!$B$5 -> 25766.4 | C12: =C10*Assumptions!$B$5 -> 322000 | D12: =D10*Assumptions!$B$5 -> 1595000 | E12: Client-side fee on top of the act. Notary keeps 100% of honoraires.
A13: Cost of revenue | B13: =-(B8*Assumptions!$B$8+B12*Assumptions!$B$7+IF(Assumptions!$B$6="Yes",B10*Assumptions!$B$7,0)) -> -2724.992 | C13: =-(C8*Assumptions!$B$8+C12*Assumptions!$B$7+IF(Assumptions!$B$6="Yes",C10*Assumptions!$B$7,0)) -> -32060 | D13: =-(D8*Assumptions!$B$8+D12*Assumptions!$B$7+IF(Assumptions!$B$6="Yes",D10*Assumptions!$B$7,0)) -> -135850
A14: Gross profit | B14: =B12+B13 -> 23041.408 | C14: =C12+C13 -> 289940 | D14: =D12+D13 -> 1459150
A15: Gross margin | B15: =IFERROR(B14/B12,0) -> 0.89424242 | C15: =IFERROR(C14/C12,0) -> 0.90043478 | D15: =IFERROR(D14/D12,0) -> 0.91482759
A17: Operating expense | B17: =-Assumptions!B26 -> -250000 | C17: =-Assumptions!C26 -> -720000 | D17: =-Assumptions!D26 -> -1850000 | E17: Y1 from Use of Funds. Y2 = 4 FTE + growth. Y3 = 10 FTE + national marketing.
A18: Net income | B18: =B14+B17 -> -226958.59 | C18: =C14+C17 -> -430060 | D18: =D14+D17 -> -390850
A20: Cumulative capital required | B20: =-B18 -> 226958.59 | C20: =-B18-C18 -> 657018.59 | D20: =-B18-C18-D18 -> 1047868.6
A22: Y3 share of addressable act volume | D22: =IFERROR(D8/'Market Sizing'!B14,0) -> 0.036666667 | E22: The plan does not require winning the market — only being where price is discovered.
A24: Series A trigger: exit Y2 at a $300–500K ARR run-rate with province-wide liquidity and the exception layer in production.

Sheet Unit Economics
A1: Unit economics
A2: Per completed act, and per notary recruited.
B4: Y1 | C4: Y2 | D4: Y3
A5: Average realised act value | B5: ='P&L 3Y'!B9 -> 1056 | C5: ='P&L 3Y'!C9 -> 1150 | D5: ='P&L 3Y'!D9 -> 1450
A6: Net revenue per act | B6: =B5*Assumptions!$B$5 -> 105.6 | C6: =C5*Assumptions!$B$5 -> 115 | D6: =D5*Assumptions!$B$5 -> 145
A7: Variable cost per act | B7: =-(Assumptions!$B$8+B6*Assumptions!$B$7+IF(Assumptions!$B$6="Yes",B5*Assumptions!$B$7,0)) -> -11.168 | C7: =-(Assumptions!$B$8+C6*Assumptions!$B$7+IF(Assumptions!$B$6="Yes",C5*Assumptions!$B$7,0)) -> -11.45 | D7: =-(Assumptions!$B$8+D6*Assumptions!$B$7+IF(Assumptions!$B$6="Yes",D5*Assumptions!$B$7,0)) -> -12.35
A8: Gross profit per act | B8: =B6+B7 -> 94.432 | C8: =C6+C7 -> 103.55 | D8: =D6+D7 -> 132.65
A9: Blended client CAC | B9: =Assumptions!B25 -> 163.93443 | C9: =Assumptions!C25 -> 55 | D9: =Assumptions!D25 -> 40 | E9: Y1 = marketing spend ÷ acts. Y2–Y3 assume organic carnet SEO and zero-CAC referral channels compound.
A10: Contribution per act (after CAC) | B10: =B8-B9 -> -69.502426 | C10: =C8-C9 -> 48.55 | D10: =D8-D9 -> 92.65 | E10: Negative in Y1 — that is what a year-one marketplace looks like. Positive from Y2.
A12: NOTARY (SUPPLY-SIDE) ECONOMICS
A13: Notary acquisition cost | B13: ='Use of Funds'!C10/Assumptions!B20 -> 500 | E13: Field sales, congrès, travel — from the Use of Funds notary line.
A14: Acts per active notary per year | B14: 20
A15: Expected notary tenure (years) | B15: 3
A16: Annual gross profit per notary | B16: =B14*C8 -> 2071
A17: Notary LTV (3 years, undiscounted) | B17: =B16*B15 -> 6213
A18: LTV / CAC | B18: =IFERROR(B17/B13,0) -> 12.426
A19: Payback (acts required) | B19: =IFERROR(B13/C8,0) -> 4.8285852
A21: Repeat-purchase note: a client buys a will roughly once a decade. Client retention is NOT the flywheel.
A22: The durable assets are the notary network, organic capture from the public carnet, and zero-CAC referral partners.

Sheet Market Sizing
A1: Market sizing — bottom up
A2: Québec only. Sources cited per line. Volumes are estimates, offered as scale rather than precision.
A4: TAM — THE QUÉBEC NOTARIAL PROFESSION
A5: Practising notaries in Québec | B5: 3900 | F5: Source: Chambre des notaires du Québec (~3,800–3,913 reported).
A6: Est. annual professional fees per notary | B6: 300000 | F6: Order-of-magnitude estimate. No published per-notary figure exists.
A7: TAM — annual professional fees billed | B7: =B5*B6 -> 1170000000
A9: SAM — THE THREE BOUNDED SERVICES
A10: Service | B10: Annual volume | C10: Avg act value | D10: Annual act value
A11: Wills + protection mandates | B11: 200000 | C11: 650 | D11: =B11*C11 -> 130000000 | F11: Registre des dispositions testamentaires: 215,576 registrations 2017-18; >6M wills held.
A12: Procurations | B12: 50000 | C12: 295 | D12: =B12*C12 -> 14750000 | F12: Estimate. No published volume.
A13: Refinancing (new hypothec) | B13: 50000 | C13: 2000 | D13: =B13*C13 -> 100000000 | F13: Inferred: ~1.2M Canadian fixed mortgages renewing 2025 (CMHC), QC ~20%, subset refinancing.
A14: SAM — three bounded services | B14: =SUM(B11:B13) -> 300000 | D14: =SUM(D11:D13) -> 244750000
A16: SOM — YEAR 3
A17: Acts completed, Y3 | B17: ='P&L 3Y'!D8 -> 11000
A18: Share of SAM volume | B18: =IFERROR(B17/B14,0) -> 0.036666667
A20: PHASE 3 HORIZON — BEYOND THE THREE SERVICES
A21: Residential closings, Québec (annual) | B21: 90000 | C21: 2500 | D21: =B21*C21 -> 225000000 | F21: APCIQ: 90,369 residential sales province-wide 2024. Fees 1,500–3,500 $.
A22: → This one category alone exceeds the current SAM.
A24: Civil-law notariat beyond Québec
A25: The International Union of Notaries spans ~90 member states — France, Belgium, Switzerland, most of Latin America —
A26: all built on the same instrument. That is where a 100× claim actually lives; not in avoiding a car trip.
